abci/__init__.py
abci/application.py
abci/encoding.py
abci/server.py
abci/utils.py
github/__init__.py
github/com/__init__.py
github/com/gogo/__init__.py
github/com/gogo/protobuf/__init__.py
github/com/gogo/protobuf/gogoproto/__init__.py
github/com/gogo/protobuf/gogoproto/gogo_pb2.py
github/com/tendermint/__init__.py
github/com/tendermint/tendermint/__init__.py
github/com/tendermint/tendermint/abci/__init__.py
github/com/tendermint/tendermint/abci/types/__init__.py
github/com/tendermint/tendermint/abci/types/types_pb2.py
github/com/tendermint/tendermint/crypto/__init__.py
github/com/tendermint/tendermint/crypto/merkle/__init__.py
github/com/tendermint/tendermint/crypto/merkle/merkle_pb2.py
github/com/tendermint/tendermint/libs/__init__.py
github/com/tendermint/tendermint/libs/common/__init__.py
github/com/tendermint/tendermint/libs/common/types_pb2.py
github/com/tendermint/tmlibs/__init__.py
github/com/tendermint/tmlibs/common/__init__.py
github/com/tendermint/tmlibs/common/types_pb2.py
bigchaindb_abci-0.7.1.dist-info/LICENSE
bigchaindb_abci-0.7.1.dist-info/METADATA
bigchaindb_abci-0.7.1.dist-info/WHEEL
bigchaindb_abci-0.7.1.dist-info/top_level.txt
bigchaindb_abci-0.7.1.dist-info/RECORD
