Metadata-Version: 2.1
Name: bigchaindb-abci
Version: 0.7.1
Summary: Python based ABCI Server for Tendermint
Home-page: https://github.com/davebryson/py-abci
Author: Dave Bryson
License: Apache 2.0
Keywords: blockchain tendermint abci
Platform: UNKNOWN
Classifier: Development Status :: 3 - Alpha
Classifier: Intended Audience :: Developers
Classifier: License :: OSI Approved :: Apache Software License
Classifier: Programming Language :: Python :: 3.6
Requires-Python: >=3.6
Requires-Dist: protobuf (>=3.6.1)
Requires-Dist: gevent (>=1.3.7)
Requires-Dist: colorlog (>=3.1.4)
Requires-Dist: pytest (>=3.10.0)
Requires-Dist: pytest-pythonpath (>=0.7.3)
Requires-Dist: pytest-cov (>=2.6.0)
